las_geoh5/__init__.py
las_geoh5/_version.py
las_geoh5/export_files/__init__.py
las_geoh5/export_files/driver.py
las_geoh5/export_files/uijson.py
las_geoh5/export_las.py
las_geoh5/import_directories/__init__.py
las_geoh5/import_directories/driver.py
las_geoh5/import_directories/uijson.py
las_geoh5/import_files/__init__.py
las_geoh5/import_files/driver.py
las_geoh5/import_files/params.py
las_geoh5/import_files/uijson.py
las_geoh5/import_las.py
las_geoh5/scripts/__init__.py
las_geoh5/scripts/geoh5_to_las.py
las_geoh5/scripts/las_to_geoh5.py
las_geoh5/uijson/__init__.py
las_geoh5/uijson/write_uijson.py
las_geoh5-assets/__init__.py
las_geoh5-assets/uijson/export_las_files.ui.json
las_geoh5-assets/uijson/import_las_directories.ui.json
las_geoh5-assets/uijson/import_las_files.ui.json
las_geoh5-0.3.2.dist-info/METADATA
las_geoh5-0.3.2.dist-info/WHEEL
las_geoh5-0.3.2.dist-info/entry_points.txt
las_geoh5-0.3.2.dist-info/licenses/LICENSE
las_geoh5-0.3.2.dist-info/licenses/docs/source/THIRD_PARTY_SOFTWARE.rst
las_geoh5-0.3.2.dist-info/RECORD
