Metadata-Version: 2.4
Name: las-geoh5
Version: 0.3.2
Summary: Las/Geoh5 conversion
License-Expression: MIT
License-File: LICENSE
License-File: docs/source/THIRD_PARTY_SOFTWARE.rst
Keywords: geology,geophysics,earth sciences,io,data,interoperability
Author: Mira Geoscience
Author-email: support@mirageoscience.com
Maintainer: Benjamin Kary
Maintainer-email: benjamink@mirageoscience.com
Requires-Python: >=3.10,<4.0
Classifier: Development Status :: 4 - Beta
Classifier: Intended Audience :: Science/Research
Classifier: Natural Language :: English
Classifier: Operating System :: MacOS
Classifier: Operating System :: Microsoft :: Windows
Classifier: Operating System :: POSIX
Classifier: Operating System :: Unix
Classifier: Programming Language :: Python
Classifier: Programming Language :: Python :: 3
Classifier: Programming Language :: Python :: 3.10
Classifier: Programming Language :: Python :: 3.11
Classifier: Programming Language :: Python :: 3.12
Classifier: Programming Language :: Python :: 3.13
Classifier: Programming Language :: Python :: 3.14
Classifier: Topic :: Scientific/Engineering
Classifier: Topic :: Scientific/Engineering :: Mathematics
Classifier: Topic :: Scientific/Engineering :: Physics
Requires-Dist: geoh5py (>=0.12.0b5,<0.13.dev)
Requires-Dist: lasio (==0.31.*)
Requires-Dist: numpy (>=1.26.0,<1.27.0)
Requires-Dist: pydantic (>=2.5.2,<3.0.0)
Requires-Dist: tqdm (>=4.66.1,<5.0.0)
Project-URL: Documentation, https://mirageoscience-las-geoh5.readthedocs-hosted.com/
Project-URL: Homepage, https://www.mirageoscience.com/mining-industry-software/python-integration/
Project-URL: Repository, https://github.com/MiraGeoscience/las-geoh5
